<?xml version = '1.0' encoding = 'UTF-8'?>
<relationalModel class="oracle.dbtools.crest.model.design.relational.RelationalDesign" name="Relational_1" id="1F8EA3E9-0AD5-733E-7FC1-107C17677706" mainViewID="29FF30FB-E258-19FD-5CD5-865515B91D25">
<createdBy>user</createdBy>
<createdTime>2024-11-08 02:06:14 UTC</createdTime>
<ownerDesignName>class</ownerDesignName>
<shouldBeOpen>false</shouldBeOpen>
<selectedRDBMSSite>79C73AAF-E1A7-E669-7DF0-025EE81A2AFC</selectedRDBMSSite>
<importConnectionStamps>
<importConnectionStamp class="oracle.dbtools.crest.imports.DBConnectionStamp">
<connName>로컬-HR</connName>
<connUser>HR</connUser>
<connType>1</connType>
</importConnectionStamp>
</importConnectionStamps>
</relationalModel>
